boatswain/__init__.py
boatswain/bcolors.py
boatswain/boatswain.py
boatswain/cli.py
boatswain/display.py
boatswain/dynamic_string_message.py
boatswain/errors.py
boatswain/timed_progress_bar.py
boatswain/util.py
boatswain-1.0.4.dist-info/LICENSE
boatswain-1.0.4.dist-info/METADATA
boatswain-1.0.4.dist-info/WHEEL
boatswain-1.0.4.dist-info/entry_points.txt
boatswain-1.0.4.dist-info/top_level.txt
boatswain-1.0.4.dist-info/RECORD
