Metadata-Version: 2.1
Name: boatswain
Version: 1.0.4
Summary: Yaml based way to build Docker images.
Home-page: https://github.com/nlesc-sherlock/boatswain
Author: Berend Weel
Author-email: b.weel@esiencecenter.nl
License: Apache Software License
Platform: any
Classifier: Programming Language :: Python
Classifier: Programming Language :: Python :: 2
Classifier: Programming Language :: Python :: 2.7
Classifier: Programming Language :: Python :: 3
Classifier: Programming Language :: Python :: 3.3
Classifier: Programming Language :: Python :: 3.4
Classifier: Programming Language :: Python :: 3.5
Classifier: Programming Language :: Python :: 3.6
Classifier: Programming Language :: Python :: 3.7
Classifier: Development Status :: 5 - Production/Stable
Classifier: Natural Language :: English
Classifier: Intended Audience :: Developers
Classifier: License :: OSI Approved :: Apache Software License
Classifier: Operating System :: OS Independent
Classifier: Topic :: Software Development :: Libraries :: Python Modules
Requires-Dist: setuptools (>=30)
Requires-Dist: docker (<5.0.0,>=3.0.0)
Requires-Dist: PyYAML (>=4.2b1)
Requires-Dist: progressbar2 (<4.0.0,>=3.16.0)
Requires-Dist: six (<2.0.0,>=1.10.0)
Provides-Extra: registry
Requires-Dist: docker-registry-client (>=0.5.1) ; extra == 'registry'
Provides-Extra: test
Requires-Dist: pytest ; extra == 'test'
Requires-Dist: pytest-flake8 ; extra == 'test'
Requires-Dist: pytest-cov ; extra == 'test'
Provides-Extra: windows
Requires-Dist: pywin32 (==224) ; extra == 'windows'
